csvcomparetool/__init__.py
csvcomparetool/cli.py
csvcomparetool/csvcomparetool.py
csvcomparetool/version.py
csv_compare_tool-1.0.3.dist-info/LICENSE.txt
csv_compare_tool-1.0.3.dist-info/METADATA
csv_compare_tool-1.0.3.dist-info/WHEEL
csv_compare_tool-1.0.3.dist-info/top_level.txt
csv_compare_tool-1.0.3.dist-info/RECORD
