Metadata-Version: 2.1
Name: csv-compare-tool
Version: 1.0.3
Summary: Package to find differences between two CSV files
Author: Andrew Speciale
License: Apache License
Project-URL: Homepage, https://github.com/liquidz00/csv-compare
Project-URL: Bug Tracker, https://github.com/liquidz00/csv-compare/issues
Classifier: Programming Language :: Python
Classifier: Programming Language :: Python :: 3
Classifier: Programming Language :: Python :: 3.8
Classifier: Programming Language :: Python :: 3.9
Classifier: Programming Language :: Python :: 3.10
Classifier: Programming Language :: Python :: 3.11
Classifier: Programming Language :: Python :: 3.12
Classifier: Programming Language :: Python :: Implementation :: PyPy
Classifier: Intended Audience :: System Administrators
Classifier: Topic :: Utilities
Classifier: License :: OSI Approved :: Apache Software License
Classifier: Operating System :: OS Independent
Requires-Python: >=3.8
License-File: LICENSE.txt
Requires-Dist: pandas
